examples/main.py
examples/mnist.py
scripts/analyze_profile.py
scripts/benchmark.py
scripts/benchmark_to_numpy.py
scripts/profile_ops.py
scripts/profile_test.py
scripts/run_profile.py
scripts/simple_benchmark.py
server/__init__.py
server/drawTensors.py
server/tests/__init__.py
server/tests/test_app.py
server/tests/test_docker.py
server/tests/test_docker_debug.py
server/tests/test_docker_quick.py
tensorgrad/__init__.py
tensorgrad/functions.py
tensorgrad/imgtools.py
tensorgrad/tensor.py
tensorgrad/testutils.py
tensorgrad/utils.py
tensorgrad/extras/__init__.py
tensorgrad/extras/_convolution.py
tensorgrad/extras/evaluate.py
tensorgrad/extras/expectation.py
tensorgrad/extras/polynomials.py
tensorgrad/extras/to_formula_old.py
tensorgrad/extras/to_index.py
tensorgrad/extras/to_latex.py
tensorgrad/extras/to_numpy.py
tensorgrad/extras/to_numpy_optimized.py
tensorgrad/extras/to_pytorch.py
tensorgrad/extras/to_tikz.py
tensorgrad-0.2.1.dist-info/licenses/LICENSE
tests/test_functions.py
tests/test_grads.py
tests/test_graph.py
tests/test_isomorphism.py
tests/test_jacobians.py
tests/test_matrix_calc.py
tests/test_ml.py
tests/test_powers.py
tests/test_product.py
tests/test_rename.py
tests/test_simplify.py
tests/test_tensor.py
tests/test_to_code.py
tests/test_variable.py
tests/extras/test_evaluate.py
tests/extras/test_expectation.py
tests/extras/test_polynomials.py
tests/extras/test_tikz.py
tests/extras/test_to_index.py
tests/extras/test_to_latex.py
tests/extras/test_to_numpy_optimized.py
tensorgrad-0.2.1.dist-info/METADATA
tensorgrad-0.2.1.dist-info/WHEEL
tensorgrad-0.2.1.dist-info/top_level.txt
tensorgrad-0.2.1.dist-info/RECORD
