Metadata-Version: 2.4
Name: tensorgrad
Version: 0.2.1
Summary: Tensor Network Library with Symbolic Autograd
Author-email: Thomas Ahle <lobais@gmail.com>
License:                     GNU AFFERO GENERAL PUBLIC LICENSE
Project-URL: Homepage, https://tensorcookbook.com
Project-URL: Repository, https://github.com/thomasahle/tensorgrad.git
Project-URL: Issues, https://github.com/thomasahle/tensorgrad/issues
Keywords: tensors,autograd
Classifier: Development Status :: 4 - Beta
Classifier: Programming Language :: Python
Requires-Python: >=3.10
License-File: LICENSE
Requires-Dist: networkx==3.2.1
Requires-Dist: numpy
Requires-Dist: torch
Requires-Dist: nbval
Requires-Dist: pytest
Requires-Dist: einops
Requires-Dist: pdf2image
Requires-Dist: sympy
Requires-Dist: sparse
Requires-Dist: opt_einsum
Requires-Dist: scipy
Requires-Dist: requests>=2.32.3
Requires-Dist: pydantic>=2.11.5
Requires-Dist: fastapi>=0.115.12
Requires-Dist: mangum>=0.19.0
Requires-Dist: boto3>=1.38.23
Requires-Dist: torchvision>=0.22.0
Requires-Dist: tqdm>=4.67.1
Dynamic: license-file
